nickpypi/__init__.py
nickpypi/nickpypi.py
nickpypi-0.0.4.dist-info/LICENSE
nickpypi-0.0.4.dist-info/METADATA
nickpypi-0.0.4.dist-info/WHEEL
nickpypi-0.0.4.dist-info/RECORD
