Metadata-Version: 2.1
Name: nickpypi
Version: 0.0.4
Summary: My daily functions
License: GPL
Author: Nick
Author-email: nick@nicks-technik.de
Requires-Python: >=3.11,<4.0
Classifier: License :: Other/Proprietary License
Classifier: Programming Language :: Python :: 3
Classifier: Programming Language :: Python :: 3.11
Classifier: Programming Language :: Python :: 3.12
Classifier: Programming Language :: Python :: 3.13
Requires-Dist: logging (>=0.4.9.6,<0.5.0.0)
Requires-Dist: poetry-core (>=1.9.1,<2.0.0)
Requires-Dist: pytest (>=8.3.3,<9.0.0)
Requires-Dist: requests (>=2.32.3,<3.0.0)
